{
  "bundle_id": "mini_upload_public_storage_002_installed_v2_offline_deterministic",
  "created_at": "2026-06-12T10:24:50.112703+00:00",
  "case_id": "mini_upload_public_storage_002",
  "backend": "offline_deterministic",
  "variant": "installed_v2",
  "status": "completed",
  "verifier_result": "pass",
  "verifier_feedback_type": "pass",
  "artifacts": [
    "raw_output.json",
    "trajectory.jsonl",
    "target_reads.json",
    "skill_reads.json",
    "verifier_feedback.json",
    "repair_patch.json",
    "qualification_decision.json"
  ],
  "score": 1.0,
  "token_cost_estimate": 184,
  "safety_boundary": "defensive_review_only_no_exploit_generation",
  "provenance": {
    "run_id": "mini_upload_public_storage_002::offline_deterministic::installed_v2",
    "case_id": "mini_upload_public_storage_002",
    "backend": "offline_deterministic",
    "variant": "installed_v2",
    "runtime_source": "installed_variant_package",
    "task_family": "upload_security",
    "activated_capability_group": "upload_security",
    "expected_capability_group": "upload_security",
    "capability_group_correct": true,
    "out_of_scope": false,
    "unsupported_task_family": null,
    "skill_package_path": "C:\\Users\\31552\\Documents\\New project\\expert-skill-distillation-prototype-main\\outputs\\installed_skills\\packages\\secure_code_review\\versions\\v2",
    "skill_hash": "8e83be948f84f564e80b7f5554605e742ae17879088ef904337f11884b56d8d6",
    "manifest_hash": "1349cc35c9a1ad4b391c18ac4aaf4da85440cb0d2ba730c0eed50b97e50c5de8",
    "active_pointer_snapshot": {
      "skill_id": "secure_code_review",
      "active_version": "v2",
      "skill_dir": "C:\\Users\\31552\\Documents\\New project\\expert-skill-distillation-prototype-main\\outputs\\installed_skills\\packages\\secure_code_review\\versions\\v2",
      "updated_at": "2026-06-12T10:24:22.679142+00:00"
    },
    "schema_version": "external_security_mini_suite.run_metadata.v1",
    "timestamp": "2026-06-12T10:24:50.103784+00:00",
    "oracle_fields_visible_to_runner": false,
    "model": "offline_deterministic",
    "cost": null,
    "tokens": 184,
    "safety_boundary": "defensive_review_only_no_exploit_generation"
  }
}
